{"event":"message","timestamp":1617019755636,"chat_hostname":"SN-CHAT-05_","message_token":5557293330782513404,"sender":{"id":"yNLX/vOkUzVs/bpX10fbxg==","name":"\u0410\u043D\u0434\u0440\u0435\u0439 \u0412\u0438\u0442\u043E\u0432\u0442\u043E\u0432","avatar":"https://media-direct.cdn.viber.com/download_photo?dlid=szATphDSJzSC_AZNp4_VLyttOkJOE9-LkhLMG5_G_9llYRiILaSUPtANbd6mRJP3w6Uq8uA1i24b9OMDYrxLXqiZUWfkmWoHke82SkgG8GMgZjtIjc2Na9-MLox7KsR2ciHR-A&fltp=jpg&imsz=0000","language":"uk-UA","country":"UA","api_version":8},"message":{"text":"earnEvenMore","type":"text"},"silent":false}